{"order_id":74631,"product":"Headphones","price":2993.06,"timestamp":"2026-04-17 23:30:38"}
{"order_id":40894,"product":"Headphones","price":980.1,"timestamp":"2026-04-17 23:30:39"}
{"order_id":28624,"product":"Headphones","price":374.22,"timestamp":"2026-04-17 23:30:39"}
{"order_id":36043,"product":"Tablet","price":1006.09,"timestamp":"2026-04-17 23:30:40"}
{"order_id":93749,"product":"Smartwatch","price":96.06,"timestamp":"2026-04-17 23:30:40"}
{"order_id":58249,"product":"Tablet","price":94.71,"timestamp":"2026-04-17 23:30:41"}
{"order_id":76718,"product":"Smartphone","price":50.77,"timestamp":"2026-04-17 23:30:41"}
{"order_id":72919,"product":"Headphones","price":651.02,"timestamp":"2026-04-17 23:30:42"}
{"order_id":42058,"product":"Tablet","price":883.68,"timestamp":"2026-04-17 23:30:42"}
{"order_id":92686,"product":"Smartphone","price":1117.25,"timestamp":"2026-04-17 23:30:43"}
{"order_id":49416,"product":"Smartwatch","price":619.32,"timestamp":"2026-04-17 23:30:43"}
{"order_id":62185,"product":"Headphones","price":426.45,"timestamp":"2026-04-17 23:30:44"}
{"order_id":24944,"product":"Smartwatch","price":3726.75,"timestamp":"2026-04-17 23:30:44"}
{"order_id":59139,"product":"Smartphone","price":132.96,"timestamp":"2026-04-17 23:30:45"}
{"order_id":59141,"product":"Smartphone","price":198.91,"timestamp":"2026-04-17 23:30:46"}
{"order_id":41494,"product":"Laptop","price":776.32,"timestamp":"2026-04-17 23:30:46"}
{"order_id":75842,"product":"Tablet","price":434.0,"timestamp":"2026-04-17 23:30:47"}
{"order_id":75872,"product":"Laptop","price":52.79,"timestamp":"2026-04-17 23:30:47"}
{"order_id":42989,"product":"Smartwatch","price":387.9,"timestamp":"2026-04-17 23:30:48"}
{"order_id":31679,"product":"Smartwatch","price":1069.02,"timestamp":"2026-04-17 23:30:48"}
{"order_id":70776,"product":"Smartphone","price":300.72,"timestamp":"2026-04-17 23:30:49"}
{"order_id":28232,"product":"Smartwatch","price":246.71,"timestamp":"2026-04-17 23:30:49"}
{"order_id":65809,"product":"Smartphone","price":77.11,"timestamp":"2026-04-17 23:30:50"}
{"order_id":92719,"product":"Headphones","price":619.79,"timestamp":"2026-04-17 23:30:50"}
{"order_id":53688,"product":"Laptop","price":515.47,"timestamp":"2026-04-17 23:30:51"}
{"order_id":47210,"product":"Tablet","price":298.65,"timestamp":"2026-04-17 23:30:51"}
{"order_id":28641,"product":"Laptop","price":1177.26,"timestamp":"2026-04-17 23:30:52"}
{"order_id":67226,"product":"Smartphone","price":1090.46,"timestamp":"2026-04-17 23:30:52"}
{"order_id":67679,"product":"Smartphone","price":159.37,"timestamp":"2026-04-17 23:30:53"}
{"order_id":22285,"product":"Smartwatch","price":642.14,"timestamp":"2026-04-17 23:30:53"}
{"order_id":44661,"product":"Headphones","price":95.82,"timestamp":"2026-04-17 23:30:54"}
{"order_id":28617,"product":"Headphones","price":1056.92,"timestamp":"2026-04-17 23:30:55"}
{"order_id":87034,"product":"Smartphone","price":1011.3,"timestamp":"2026-04-17 23:30:55"}
{"order_id":69968,"product":"Smartphone","price":888.23,"timestamp":"2026-04-17 23:30:56"}
{"order_id":35065,"product":"Tablet","price":1127.85,"timestamp":"2026-04-17 23:30:56"}
{"order_id":70336,"product":"Tablet","price":585.07,"timestamp":"2026-04-17 23:30:57"}
{"order_id":45102,"product":"Tablet","price":338.93,"timestamp":"2026-04-17 23:30:57"}
{"order_id":65996,"product":"Tablet","price":561.08,"timestamp":"2026-04-17 23:30:58"}
{"order_id":49672,"product":"Smartphone","price":528.89,"timestamp":"2026-04-17 23:30:58"}
{"order_id":47410,"product":"Laptop","price":857.02,"timestamp":"2026-04-17 23:30:59"}
{"order_id":87672,"product":"Laptop","price":339.43,"timestamp":"2026-04-17 23:30:59"}
{"order_id":27024,"product":"Headphones","price":511.9,"timestamp":"2026-04-17 23:31:00"}
{"order_id":56681,"product":"Tablet","price":4121.29,"timestamp":"2026-04-17 23:31:00"}
{"order_id":40307,"product":"Tablet","price":434.98,"timestamp":"2026-04-17 23:31:01"}
{"order_id":57366,"product":"Laptop","price":441.63,"timestamp":"2026-04-17 23:31:02"}
{"order_id":69290,"product":"Laptop","price":967.13,"timestamp":"2026-04-17 23:31:02"}
{"order_id":76888,"product":"Smartwatch","price":360.43,"timestamp":"2026-04-17 23:31:03"}
{"order_id":15624,"product":"Smartwatch","price":587.89,"timestamp":"2026-04-17 23:31:03"}
{"order_id":98151,"product":"Tablet","price":453.46,"timestamp":"2026-04-17 23:31:04"}
{"order_id":58163,"product":"Smartphone","price":133.35,"timestamp":"2026-04-17 23:31:04"}
{"order_id":61654,"product":"Smartwatch","price":1097.83,"timestamp":"2026-04-17 23:31:05"}
{"order_id":94078,"product":"Laptop","price":341.92,"timestamp":"2026-04-17 23:31:05"}
{"order_id":23694,"product":"Headphones","price":1091.1,"timestamp":"2026-04-17 23:31:06"}
{"order_id":58150,"product":"Smartphone","price":227.57,"timestamp":"2026-04-17 23:31:06"}
