{"order_id":82504,"product":"Smartphone","price":304.18,"timestamp":"2026-04-17 23:40:55"}
{"order_id":90795,"product":"Smartphone","price":332.14,"timestamp":"2026-04-17 23:40:56"}
{"order_id":61005,"product":"Smartphone","price":317.48,"timestamp":"2026-04-17 23:40:56"}
{"order_id":91109,"product":"Headphones","price":146.26,"timestamp":"2026-04-17 23:40:57"}
{"order_id":24563,"product":"Headphones","price":529.21,"timestamp":"2026-04-17 23:40:57"}
{"order_id":50167,"product":"Headphones","price":3092.54,"timestamp":"2026-04-17 23:40:58"}
{"order_id":15041,"product":"Laptop","price":1067.52,"timestamp":"2026-04-17 23:40:58"}
{"order_id":25847,"product":"Laptop","price":1145.06,"timestamp":"2026-04-17 23:40:59"}
{"order_id":80863,"product":"Tablet","price":1089.58,"timestamp":"2026-04-17 23:40:59"}
{"order_id":23008,"product":"Laptop","price":967.99,"timestamp":"2026-04-17 23:41:00"}
{"order_id":73129,"product":"Smartphone","price":762.25,"timestamp":"2026-04-17 23:41:00"}
{"order_id":64077,"product":"Laptop","price":641.02,"timestamp":"2026-04-17 23:41:01"}
{"order_id":24420,"product":"Tablet","price":104.23,"timestamp":"2026-04-17 23:41:01"}
{"order_id":84359,"product":"Tablet","price":406.79,"timestamp":"2026-04-17 23:41:02"}
{"order_id":77916,"product":"Smartwatch","price":360.74,"timestamp":"2026-04-17 23:41:02"}
{"order_id":42178,"product":"Headphones","price":207.9,"timestamp":"2026-04-17 23:41:03"}
{"order_id":42040,"product":"Laptop","price":134.43,"timestamp":"2026-04-17 23:41:03"}
{"order_id":21937,"product":"Laptop","price":482.51,"timestamp":"2026-04-17 23:41:04"}
{"order_id":44750,"product":"Laptop","price":4740.28,"timestamp":"2026-04-17 23:41:04"}
{"order_id":30426,"product":"Tablet","price":622.29,"timestamp":"2026-04-17 23:41:05"}
{"order_id":17127,"product":"Smartphone","price":52.69,"timestamp":"2026-04-17 23:41:05"}
{"order_id":22859,"product":"Smartphone","price":857.94,"timestamp":"2026-04-17 23:41:06"}
